quickScheduler/__init__.py
quickScheduler/backend/__init__.py
quickScheduler/backend/api.py
quickScheduler/backend/database.py
quickScheduler/backend/models.py
quickScheduler/backend/scheduler.py
quickScheduler/backend/system_stats.py
quickScheduler/frontend/__init__.py
quickScheduler/frontend/app.py
quickScheduler/frontend/auth.py
quickScheduler/frontend/templates/base.html
quickScheduler/frontend/templates/index.html
quickScheduler/frontend/templates/job_details.html
quickScheduler/frontend/templates/job_history.html
quickScheduler/frontend/templates/job_history_all.html
quickScheduler/frontend/templates/job_log.html
quickScheduler/frontend/templates/login.html
quickScheduler/frontend/templates/stats_dashboard.html
quickScheduler/frontend/templates/task_details.html
quickScheduler/frontend/templates/tasks.html
quickScheduler/utils/__init__.py
quickScheduler/utils/datetime_utils.py
quickScheduler/utils/email_utils.py
quickScheduler/utils/log_monitor.py
quickScheduler/utils/subprocess_runner.py
quickScheduler/utils/triggers.py
quickScheduler/utils/yaml_config.py
quick_scheduler-1.1.2.dist-info/licenses/LICENSE
quick_scheduler-1.1.2.dist-info/METADATA
quick_scheduler-1.1.2.dist-info/WHEEL
quick_scheduler-1.1.2.dist-info/top_level.txt
quick_scheduler-1.1.2.dist-info/RECORD
