Metadata-Version: 2.4
Name: quick-scheduler
Version: 1.1.2
Summary: A quick task scheduling library
Author-email: Yes DrX <yes.drx@gmail.com>
License: MIT License
Project-URL: Homepage, https://github.com/YesDrX/QuickScheduler
Project-URL: Bug Tracker, https://github.com/YesDrX/QuickScheduler/issues
Classifier: Programming Language :: Python :: 3
Classifier: License :: OSI Approved :: MIT License
Classifier: Operating System :: OS Independent
License-File: LICENSE
Requires-Dist: pydantic>=2.0
Requires-Dist: sqlalchemy>=2.0.0
Requires-Dist: psutil
Requires-Dist: pathvalidate
Requires-Dist: pytz
Requires-Dist: httpx
Requires-Dist: tzlocal
Requires-Dist: fastapi
Requires-Dist: pyyaml
Requires-Dist: ruamel.yaml
Requires-Dist: click
Requires-Dist: pandas
Requires-Dist: markdown
Requires-Dist: dill
Requires-Dist: requests
Requires-Dist: itsdangerous
Requires-Dist: bcrypt
Requires-Dist: uvicorn
Requires-Dist: jinja2
Requires-Dist: python-multipart
Requires-Dist: fuzzywuzzy
Dynamic: license-file
